{
    "adult": false,
    "backdrop_path": "/bDFb2S3jPm3vGfiHkaf1E2ZabBC.jpg",
    "genre_ids": [
        16,
        35
    ],
    "id": 68188,
    "origin_country": [
        "JP"
    ],
    "original_language": "ja",
    "original_name": "私がモテてどうすんだ",
    "overview": "女高中生芹沼花依，是個看到男生之間的親密關係就會產生妄想的腐女。某天，她由於喜愛的動畫角色死亡，受到衝擊而體重驟減，結果卻因此而受到校內 4 位美男子的約會邀請。「明明和我在一起什麼的一點也不萌，難道我的春天到來了嗎！？」",
    "popularity": 25.37,
    "poster_path": "output/tvshows/私がモテてどうすんだ (2016)/poster.jpg",
    "first_air_date": "2016-10-07",
    "name": "我太受歡迎了該怎麼辦",
    "vote_average": 8.4,
    "vote_count": 296
}