{
    "adult": false,
    "backdrop_path": "/5KwDfIM7UO2vPXr4E7JEmeiFxwU.jpg",
    "genre_ids": [
        16,
        12,
        878
    ],
    "id": 98299,
    "original_language": "ja",
    "original_title": "デジモンアドベンチャー02 前編・デジモンハリケーン上陸!!／後編・超絶進化!!黄金のデジメンタル",
    "overview": "美國的小朋友華勒斯（又譯華力斯、華萊士、沃利斯）擁有了雙胞胎數碼獸，大耳獸（軟糖獸）和黑大耳獸（巧克力獸），但其中一隻卻莫名其妙地消失了。若干年之後華勒斯長大了，此時正是2002年暑假，小光和阿岳來到美國旅行，碰上了那隻失蹤的數碼獸。他們聯繫了大輔，大輔趕來的時候，碰上了華勒斯，6人決定一起面對那隻數碼獸，卻不敵其究極體的實力。最終小光和阿岳的數碼獸進化為究極體，為大輔的數碼獸製作了代表奇蹟的數碼裝甲，並為華勒斯的數碼獸製作了代表命運的數碼裝甲，使V仔獸和軟糖獸裝甲進化，打倒了巧克力獸。",
    "popularity": 9.731,
    "poster_path": "output/movie/デジモンアドベンチャー02 前編・デジモンハリケーン上陸!!／後編・超絶進化!!黄金のデジメンタル (2000)/poster.jpg",
    "release_date": "2000-07-08",
    "title": "數碼寶貝大冒險02 前篇 暴龍旋風登陸 危機再現!／後篇 超絕進化!!黃金裝甲最強之力!",
    "video": false,
    "vote_average": 7,
    "vote_count": 37
}