{
    "adult": false,
    "backdrop_path": "/1FiPbrqSAOMHZus9zE9HPQyG5Ve.jpg",
    "genre_ids": [
        16,
        35,
        9648,
        18
    ],
    "id": 31741,
    "origin_country": [
        "JP"
    ],
    "original_language": "ja",
    "original_name": "ブラック・ブラッド・ブラザーズ",
    "overview": "1997 年香港，因突發的\"九龍血統\"暴走事件，令香港陷入了毀滅邊緣。這就是所謂的九龍衝擊，在當時人類與吸血鬼面對共同的敵人九龍血統，拉起了共同戰線。在這場被稱為香港聖戰的戰爭當中，有一個以一把鍍銀長刀砍殺無數九龍血統吸血鬼，並打倒了始祖九龍王的吸血鬼，他就是被人稱為銀刀的望月次郎。由於次郎等人的活躍表現，結束了香港聖戰。十年後，望月次郎和他的弟弟望月小太郎，正前往位於橫濱海岸的\"特區\"……",
    "popularity": 9.033,
    "poster_path": "output/tvshows/ブラック・ブラッド・ブラザーズ (2006)/poster.jpg",
    "first_air_date": "2006-09-08",
    "name": "黑血兄弟",
    "vote_average": 6.7,
    "vote_count": 19
}