{
    "adult": false,
    "backdrop_path": "/mG4cMeFBphnzQrAjE6X1hbhXe4q.jpg",
    "genre_ids": [
        16,
        35,
        10759
    ],
    "id": 22831,
    "origin_country": [
        "JP"
    ],
    "original_language": "ja",
    "original_name": "ガンスミスキャッツ",
    "overview": "拉莉（Rally Vincent）與小美（May）是一對動作型與技術型的搭配（神槍手+爆彈專家），兩人性格迥異，但齊心協力的時候殺傷力極大。\n\n賞金獵人拉莉·雲遜，19歲，以追緝逃犯維護生。聞著硝煙味才能睡著，睡著後無論怎麼吵/被畫貓臉/被搖晃，都不會醒，但是只要有人動她的槍就會立即反應並開槍。開著一家槍店，但生意慘淡。堪稱新車殺手，每次換了新車都會在任務中報廢……她一步步把罪犯逼得走投無路，也把自己推向險惡的邊緣……\n\n自稱爆彈專家、拉莉稱之為爆彈狂魔的小美，17歲，因曾在“紫貓館”工作，使得外表停留在13歲左右的可愛小孩模樣。身上總帶著許多旁人看起來很奇怪的炸彈零件，豐富的炸彈知識是其男友（35歲）健·達基所教，因為身型矮小，因此對火藥味非常敏感。",
    "popularity": 8.398,
    "poster_path": "output/tvshows/ガンスミスキャッツ (1995)/poster.jpg",
    "first_air_date": "1995-11-01",
    "name": "貓眼女槍手",
    "vote_average": 7.2,
    "vote_count": 11
}