{
    "adult": false,
    "backdrop_path": "/iW4dd1BuAhtYSKMLtt3vGX4C1um.jpg",
    "genre_ids": [
        10751,
        16,
        12,
        878,
        14
    ],
    "id": 162092,
    "original_language": "ja",
    "original_title": "のび太と翼の勇者たち",
    "overview": "地方名稱取自烏托邦。鳥進化後，成為「鳥人」。這是鳥和鳥人們的樂園，但是鳥人覺得虐待鳥類的種族的人很多。牠們的其中一個雀鳥通道與大雄的學校後山連接一起。",
    "popularity": 16.543,
    "poster_path": "output/movie/のび太と翼の勇者たち (2001)/poster.jpg",
    "release_date": "2001-03-10",
    "title": "電影哆啦A夢：大雄與翼之勇者",
    "video": false,
    "vote_average": 7.4,
    "vote_count": 37
}