{
    "adult": false,
    "backdrop_path": "/aaAy3CGWCrLAIvNMNv7XXoXXmsG.jpg",
    "genre_ids": [
        16,
        10759,
        35
    ],
    "id": 60810,
    "origin_country": [
        "JP"
    ],
    "original_language": "ja",
    "original_name": "星刻の竜騎士",
    "overview": "「安薩里邦騎龍學院」，是在「育龍之國」羅雷亞蒙騎士國所創立的育龍人養成設施。\n\n上級班一年級的亞修‧布雷克，有著特殊的才能，但因至今作為夥伴的幼龍遲未誕生之故，而被認為是問題學生。在一個偶發事件當中，亞修的龍伴侶終於誕生，但不知何故卻有著美少女的身姿，並對亞修宣言「我才是你的飼主！」。於是亞修與不被駕馭的夥伴 艾可共同展開風波不斷的學院生活。",
    "popularity": 11.351,
    "poster_path": "output/tvshows/星刻の竜騎士 (2014)/poster.jpg",
    "first_air_date": "2014-04-05",
    "name": "星刻龍騎士",
    "vote_average": 7,
    "vote_count": 24
}