{
    "adult": false,
    "backdrop_path": "/jvb3uxYWvWuoS4vBZXfQWbDRy6o.jpg",
    "genre_ids": [
        16
    ],
    "id": 224207,
    "origin_country": [
        "JP"
    ],
    "original_language": "ja",
    "original_name": "BanG Dream! It's MyGO!!!!!",
    "overview": "「妳願意一輩子和我一起組樂團嗎？」高一的春天已進入尾聲。在羽丘女子學園，人人都有組樂團。而晚入學的愛音為了盡早融入班上，也急著想找尋組樂團的同伴。過程中，愛音得知「羽丘的怪女生」燈還沒有組樂團，於是試著向她搭話……。滿身是傷又狼狽的，屬於我們的＜音樂（吶喊）＞即便迷失方向也無所謂，只要有所前進就好！",
    "popularity": 20.833,
    "poster_path": "output/tvshows/BanG Dream! It's MyGO!!!!! (2023)/poster.jpg",
    "first_air_date": "2023-06-29",
    "name": "BanG Dream! It's MyGO!!!!!",
    "vote_average": 8.2,
    "vote_count": 16
}