{
    "adult": false,
    "backdrop_path": "/7oHXdbso6p7xuNAjAKp5xHyjB7y.jpg",
    "genre_ids": [
        16
    ],
    "id": 77237,
    "origin_country": [
        "JP"
    ],
    "original_language": "ja",
    "original_name": "ワカコ酒",
    "overview": "從女性角色的角度來描繪飲食生活的小品。重點不在於料理或是酒的詳細考察，而是放鬆身心的療癒感為重點。\n\n　　26歲的OL和歌子每天下班最大樂趣就是發掘居酒屋或小吃店，一個人盡情享受美酒與佳餚。隨著社會風氣的改變，現在有越來越多女性會獨自前往酒吧或居酒屋暢飲。",
    "popularity": 3.852,
    "poster_path": "output/tvshows/ワカコ酒 (2015)/poster.jpg",
    "first_air_date": "2015-07-05",
    "name": "和歌子酒",
    "vote_average": 7.5,
    "vote_count": 6
}