{
    "adult": false,
    "backdrop_path": "/AcKnrZgsf8ea8NJWdGWlqSYTQBG.jpg",
    "genre_ids": [
        16,
        10759,
        10765
    ],
    "id": 60654,
    "origin_country": [
        "JP"
    ],
    "original_language": "ja",
    "original_name": "マギ",
    "overview": "聽說，在世界上突然此起彼伏出現的古代王朝遺蹟群「迷宮（DUNGEON）」裏，正長眠著擁有不可思議力量的、被稱作「魔人金具」之魔法道具，以及滿山金銀財寶。\n\n逃出故國的阿里巴巴，生活在沙漠中的綠洲都市——七湘裏，以勞動幹活掙取生活費。他也是個夢想著「攻略迷宮」而一獲千金的人。有一天，他碰上了擁有不可思議力量的少年阿拉丁，以及拳腳威力驚人的女奴隸摩兒迦娜。命運的安排下，他們都進了七湘裏那難以攻下的迷宮。大冒險就此揭開序幕……",
    "popularity": 30.891,
    "poster_path": "output/tvshows/マギ (2012)/poster.jpg",
    "first_air_date": "2012-10-07",
    "name": "MAGI魔奇少年",
    "vote_average": 8.6,
    "vote_count": 169
}