{
    "adult": false,
    "backdrop_path": "/dHrIOMTfsuYtIMqP7qeydNiWofE.jpg",
    "genre_ids": [
        16,
        12,
        28,
        10751,
        14,
        878
    ],
    "id": 481760,
    "original_language": "ja",
    "original_title": "デジモンアドベンチャー tri. 第6章「ぼくらの未来」",
    "overview": "秩序獸的出現使得恆常性方認為執行重啟計劃是解決現有危機的最佳方式。不過，藉助小光的身體，在意識的引導下，迪路獸表示全部的希望在緬因貓獸之中，因為緬因貓獸仍然存有大家的數據記憶。隨著解決危機的緬因貓獸的記憶被打開，代表恆常性的傑斯獸停止了「重啟」，而孩子們也做好了幹掉秩序獸的決心。此時芽心的神聖計劃發光並使得奧米加獸進化為奧米加獸慈悲模式，最終打敗了秩序獸，而緬因貓獸消失了。",
    "popularity": 7.252,
    "poster_path": "output/movie/デジモンアドベンチャー tri. 第6章「ぼくらの未来」 (2018)/poster.jpg",
    "release_date": "2018-05-05",
    "title": "數碼寶貝大冒險tri.第6章「我們的未來」",
    "video": false,
    "vote_average": 6.6,
    "vote_count": 34
}