{
    "adult": false,
    "backdrop_path": "/iLCtwLL4hmtH3o2gm3iP6I4gYqb.jpg",
    "genre_ids": [
        16,
        10759,
        10765
    ],
    "id": 67037,
    "origin_country": [
        "JP"
    ],
    "original_language": "ja",
    "original_name": "ファイナルファンタジー",
    "overview": "動畫情節發生於和《Final Fantasy V》相同，被稱為「R星」的世界。情節設定於遊戲的200年後，四顆水晶被人奪走了三顆。《Final Fantasy V》的勇者們已經成為傳說。在《Final Fantasy V》中登場的角色米德，告知了動畫中的新勇者布里茲和莉娜莉，新的邪惡勢力Deathgyunos出現於黑月當中，於是他們與飛空艇海賊團首領露珠，以及飛空艇部隊「鐵之翼」隊長瓦爾卡斯一起聯手要消滅邪惡勢力並奪回水晶。",
    "popularity": 5.718,
    "poster_path": "output/tvshows/ファイナルファンタジー (1994)/poster.jpg",
    "first_air_date": "1994-03-21",
    "name": "Final Fantasy: Legend of the Crystals",
    "vote_average": 6.6,
    "vote_count": 8
}