{
    "adult": false,
    "backdrop_path": "/uLcnCwT6y4FF7y6k8b46mJKrx85.jpg",
    "genre_ids": [
        16,
        18,
        35,
        10759
    ],
    "id": 93816,
    "origin_country": [
        "JP"
    ],
    "original_language": "ja",
    "original_name": "GREAT PRETENDER",
    "overview": "枝村真人自稱日本第一騙子，卻在試圖欺騙真正世界級的騙徒羅蘭·提耶里時，迎來超乎預料的後果。",
    "popularity": 211.852,
    "poster_path": "output/tvshows/GREAT PRETENDER (2020)/poster.jpg",
    "first_air_date": "2020-07-09",
    "name": "詐騙之王",
    "vote_average": 7.5,
    "vote_count": 98
}