{
    "adult": false,
    "backdrop_path": "/9tfG0WM9azqdOlJEu46DwONA1Ba.jpg",
    "genre_ids": [
        16,
        35
    ],
    "id": 42881,
    "origin_country": [
        "JP"
    ],
    "original_language": "ja",
    "original_name": "天地無用!GXP",
    "overview": "該作也是睽違10年再度以梶島版為基礎而製作的「梶島天地」版動畫。劇情時間點設定是在OVA版《天地無用！魎皇鬼（第3期）》結束約2年後，以GP養成學校為舞台的外傳作品。",
    "popularity": 48.33,
    "poster_path": "output/tvshows/天地無用!GXP (2002)/poster.jpg",
    "first_air_date": "2002-04-03",
    "name": "天地無用！GXP",
    "vote_average": 7.1,
    "vote_count": 10
}