{
    "adult": false,
    "backdrop_path": "/1fPsGvVfMH9gP2p1Rhb9619R5Pm.jpg",
    "genre_ids": [
        16,
        35
    ],
    "id": 34717,
    "origin_country": [
        "JP"
    ],
    "original_language": "ja",
    "original_name": "ながされて藍蘭島",
    "overview": "與父親吵架憤而離家出走的14歲男主角東方院行人，旅途中從所乘的船上跌落海中，遇到百年一次的超級暴風雨，經過了數日的漂流後，行人漂流到一個名為藍蘭島的小島上。由於島的四周布滿危險的漩渦，無法離開的行人只好暫時住在島上。然而，除了行人外，這座島上只有女性……\n\n與個性豐富的女生相處，行人害羞卻又有趣的新生活，就這樣開始了。",
    "popularity": 16.254,
    "poster_path": "output/tvshows/ながされて藍蘭島 (2007)/poster.jpg",
    "first_air_date": "2007-04-04",
    "name": "藍蘭島漂流記",
    "vote_average": 7.2,
    "vote_count": 6
}