{
    "adult": false,
    "backdrop_path": "/5bOYtdiBKBnrbfPTwZaAEJOfDmW.jpg",
    "genre_ids": [
        10759,
        16,
        18,
        10765,
        35
    ],
    "id": 22634,
    "origin_country": [
        "JP"
    ],
    "original_language": "ja",
    "original_name": "灼眼のシャナ",
    "overview": "新學期剛開始，高中生·坂井悠二一如往常過著“日常生活”。然而有一天，他冷不防遭遇紅世之王手下的侵襲。受到一名能夠把人的存在化為靈火，並吸取靈火的神秘男子法利亞格尼的攻擊。悠二的“日常”生活因此整個脫節，然而就在同一時間，一名少女出現在他面前。少女為了保護悠二不被法利亞格尼襲擊，開始與悠二一同生活。悠二滿懷感激向少女道謝，不料少女卻如此低喃：“你已經不存在了。”我已經死了？存在喪失者·悠二為何還能夠思考呢……",
    "popularity": 71.713,
    "poster_path": "output/tvshows/灼眼のシャナ (2005)/poster.jpg",
    "first_air_date": "2005-10-06",
    "name": "灼眼的夏娜",
    "vote_average": 7.4,
    "vote_count": 83
}