{
    "adult": false,
    "backdrop_path": null,
    "genre_ids": [
        10759,
        16,
        35,
        10765
    ],
    "id": 196873,
    "origin_country": [
        "JP"
    ],
    "original_language": "ja",
    "original_name": "セイバーマリオネット J to X",
    "overview": "堤拉茲星球的「人類女性復活」目標即將到來，機器人偶之後的存在意義是什麼？另外間宮小樽在萊姆、櫻桃、紅莓三人裡，開始有了「她們對我是三個人，但是我對她們卻是唯一的」的疑慮，因此面臨到要從三人裡選擇一位的局面。",
    "popularity": 6.039,
    "poster_path": "output/tvshows/セイバーマリオネット J to X (1998)/poster.jpg",
    "first_air_date": "1998-10-06",
    "name": "機械女神J to X",
    "vote_average": 7.5,
    "vote_count": 2
}