{
    "adult": false,
    "backdrop_path": "/isTQeaP6kp4lc9OBLKYGqK3ncu2.jpg",
    "genre_ids": [
        16,
        10765,
        9648,
        80
    ],
    "id": 94924,
    "origin_country": [
        "US"
    ],
    "original_language": "en",
    "original_name": "Trese",
    "overview": "在馬尼拉，超自然的黑暗力量滲透罪惡的地下世界，維繫和平的任務全靠亞歷珊卓·特萊絲一肩扛起，然而一股風暴正在悄悄醞釀。",
    "popularity": 13.123,
    "poster_path": "output/tvshows/Trese (2021)/poster.jpg",
    "first_air_date": "2021-06-11",
    "name": "靈探特萊絲",
    "vote_average": 7.2,
    "vote_count": 151
}