{
    "adult": false,
    "backdrop_path": "/78aF0EIxDdesV81ByS5PaFnqOnC.jpg",
    "genre_ids": [
        16,
        10759
    ],
    "id": 76123,
    "origin_country": [
        "JP"
    ],
    "original_language": "ja",
    "original_name": "Fate/EXTRA Last Encore",
    "overview": "原本應該是普通的校園生活，但隨著對現況違和感，主角．岸浪白野踏入了名為聖杯戰爭的零和遊戲。經過預選後共誕生了共128名Master，一但戰敗就會迎來死亡，忘記過去的岸浪白野，能在眾多Master中勝出嗎？",
    "popularity": 18.619,
    "poster_path": "output/tvshows/Fate_EXTRA Last Encore (2018)/poster.jpg",
    "first_air_date": "2018-01-27",
    "name": "Fate / EXTRA Last Encore",
    "vote_average": 7.2,
    "vote_count": 78
}