{
    "adult": false,
    "backdrop_path": "/mnNkpQ4J9bNubFQfReaI9SVV9QR.jpg",
    "genre_ids": [
        10759,
        10765,
        16,
        35
    ],
    "id": 80504,
    "origin_country": [
        "JP"
    ],
    "original_language": "ja",
    "original_name": "ゆらぎ荘の幽奈さん",
    "overview": "擁有通靈能力的男主角冬空凩，入住了溫泉公寓搖曳莊，在他的房間中有一位名為幽奈的地縛靈，除此之外、搖曳莊裡還住著多位各有魅力的美女。此後，冬空凩與諸多女性充滿笑料與鬧劇的生活便開始了……",
    "popularity": 23.382,
    "poster_path": "output/tvshows/ゆらぎ荘の幽奈さん (2018)/poster.jpg",
    "first_air_date": "2018-07-14",
    "name": "搖曳莊的幽奈小姐",
    "vote_average": 7.5,
    "vote_count": 34
}