{
    "adult": false,
    "backdrop_path": "/9Otcgt1bULYSZl4Jhc1e95eh3io.jpg",
    "genre_ids": [
        16,
        10759
    ],
    "id": 66101,
    "origin_country": [
        "JP"
    ],
    "original_language": "ja",
    "original_name": "リライト",
    "overview": "居住於這座以「文明與綠色共存」為理念而興建的都市 風祭市，天王寺瑚太朗、神戶小鳥、吉野晴彥等夥伴過著平凡的每一天。\n\n風祭市裡每年都有舉城歡慶的收穫祭。為了這個大型活動，瑚太朗開始收集新聞素材的工作，同一時間，瑚太朗的身邊也開始出現無法解釋的奇怪事件，瑚太朗著手調查這些事件，並向超自然研究會會長 千里朱音尋求幫助。但瑚太朗這時還沒有意識到，自己的行動已經和探尋那誰也不知道的「真實」聯繫在了一起。",
    "popularity": 19.643,
    "poster_path": "output/tvshows/リライト (2016)/poster.jpg",
    "first_air_date": "2016-07-02",
    "name": "Rewrite",
    "vote_average": 5.3,
    "vote_count": 16
}