{
    "adult": false,
    "backdrop_path": "/zCUVArvmCxbMDMAqrVwP6BFN3J5.jpg",
    "genre_ids": [
        16,
        10759,
        10765
    ],
    "id": 39435,
    "origin_country": [
        "JP"
    ],
    "original_language": "ja",
    "original_name": "「C」",
    "overview": "故事發生在遙遠的未來時代，日本財政陷入了巨大的危機之中，就在國家即將崩潰之時，一個名為“Sovereign Wealth Fund”的金融機構出現，成功的挽救了搖搖欲墜的日本。儘管經濟危機得到了緩解，但城市卻因長久以來的缺乏管理而陷入了混亂，失業率、自殺率和犯罪率急速上升。餘賀公麿的母親早逝，父親亦不知所踪，在舅母的撫養下長大成人的他就讀於經濟學部。家庭溫暖的缺失讓公麿十分渴望能夠擁有一個穩定的家，某一日，他在銀行中遇見了一位神秘的男子真坂木，男子以公麿的未來作為抵押，借給了公麿大量金錢，公麿就此進入了異空間“金融街”，在那裡，有許多和他一樣失去了未來的人們，靠著戰鬥來實現各自的夢想。",
    "popularity": 25.69,
    "poster_path": "output/tvshows/「C」 (2011)/poster.jpg",
    "first_air_date": "2011-04-15",
    "name": "金融C風暴",
    "vote_average": 7.8,
    "vote_count": 75
}