{
    "adult": false,
    "backdrop_path": "/bprWynwFTI2TGsFDLGLSSGvuVZ3.jpg",
    "genre_ids": [
        16,
        35,
        18,
        10765
    ],
    "id": 72911,
    "origin_country": [
        "JP"
    ],
    "original_language": "ja",
    "original_name": "ぎんぎつね",
    "overview": "　　這裡是某鎮的一間小小稻荷神社。神社第十五代繼承人．冴木真琴擁有可以看見神狐──銀太郎的神奇能力。然而這隻神狐卻是毒舌又沒幹勁。熱心助人的真琴想借用牠的力量幫助別人，然而卻……今天神社又會發生什麼故事呢？",
    "popularity": 9.203,
    "poster_path": "output/tvshows/ぎんぎつね (2013)/poster.jpg",
    "first_air_date": "2013-10-07",
    "name": "銀狐",
    "vote_average": 7.6,
    "vote_count": 8
}