{
    "adult": false,
    "backdrop_path": "/f57xInVHo95qUIHUNd4NPTj5Vva.jpg",
    "genre_ids": [
        16
    ],
    "id": 377909,
    "original_language": "ja",
    "original_title": "гғ”гӮ«гғҒгғҘгӮҰгҒЁгӮӨгғјгғ–гӮӨвҳҶгғ•гғ¬гғігӮә",
    "overview": "",
    "popularity": 4.104,
    "poster_path": "output/movie/гғ”гӮ«гғҒгғҘгӮҰгҒЁгӮӨгғјгғ–гӮӨвҳҶгғ•гғ¬гғігӮә (2013)/poster.jpg",
    "release_date": "2013-07-13",
    "title": "гғ”гӮ«гғҒгғҘгӮҰгҒЁгӮӨгғјгғ–гӮӨвҳҶгғ•гғ¬гғігӮә",
    "video": false,
    "vote_average": 6.9,
    "vote_count": 8
}