{
    "adult": false,
    "backdrop_path": "/a1b2aSq9HYLQS1poszx4QeIfuV0.jpg",
    "genre_ids": [
        10759,
        16,
        35
    ],
    "id": 44428,
    "origin_country": [
        "JP"
    ],
    "original_language": "ja",
    "original_name": "жҘҪеӢқпјҒгғҸгӮӨгғ‘гғјвҷҘгғүгғјгғ«",
    "overview": "",
    "popularity": 4.166,
    "poster_path": "output/tvshows/жҘҪеӢқпјҒгғҸгӮӨгғ‘гғјвҷҘгғүгғјгғ« (1995)/poster.jpg",
    "first_air_date": "1995-10-05",
    "name": "жҘҪеӢқпјҒгғҸгӮӨгғ‘гғјвҷҘгғүгғјгғ«",
    "vote_average": 5,
    "vote_count": 2
}