{
    "adult": false,
    "backdrop_path": "/57CWn81fUXqfendHHgQxLbmjdHH.jpg",
    "genre_ids": [
        16,
        10765,
        35
    ],
    "id": 76132,
    "origin_country": [
        "JP"
    ],
    "original_language": "ja",
    "original_name": "ミイラの飼い方",
    "overview": "柏木空的父親是一名冒險家（自稱），某天他居然從埃及寄回了一隻小木乃伊？！小小一隻又超會賣萌... 牠什麼都吃，還會幫忙做家事！？男高中生跟小木乃伊的療癒生活點滴就此展開。",
    "popularity": 15.099,
    "poster_path": "output/tvshows/ミイラの飼い方 (2018)/poster.jpg",
    "first_air_date": "2018-01-12",
    "name": "小木乃伊到我家",
    "vote_average": 8.5,
    "vote_count": 175
}