{
    "adult": false,
    "backdrop_path": "/3BgTzi0fOJifVjg1XvP16TYSD4b.jpg",
    "genre_ids": [
        16,
        10765
    ],
    "id": 81334,
    "origin_country": [
        "JP"
    ],
    "original_language": "ja",
    "original_name": "エレメントハンター",
    "overview": "2029年，人們發現地中海沿岸發生了氧元素消失的現象，之後各種元素相繼消失。受此影響，60年後，地球上的人口只剩下全盛時期的十分之一。調查表明，消失的元素去了另一個地球，為了取回消失的元素，名為「元素獵人」的組織成立了，其成員都是13歲以下的小孩，因為只有小孩才能去另外一個地球（黑暗地球）。",
    "popularity": 5.796,
    "poster_path": "output/tvshows/エレメントハンター (2009)/poster.jpg",
    "first_air_date": "2009-07-04",
    "name": "元素高手",
    "vote_average": 1,
    "vote_count": 1
}