{
    "adult": false,
    "backdrop_path": "/bnAhFfA9jqjFyRMhuasn0K7yfdK.jpg",
    "genre_ids": [
        10759,
        16,
        10765
    ],
    "id": 66987,
    "origin_country": [
        "JP"
    ],
    "original_language": "ja",
    "original_name": "ブラザーフッド ファイナルファンタジーXV",
    "overview": "描述了遊戲中登場的幾個主要角色間的羈絆，聚焦於主角和同伴少年時代的故事，通過這四個同伴的故事描繪《 Final Fantasy XV》的廣袤世界。",
    "popularity": 23.926,
    "poster_path": "output/tvshows/ブラザーフッド ファイナルファンタジーXV (2016)/poster.jpg",
    "first_air_date": "2016-03-30",
    "name": "兄弟情 Final Fantasy XV",
    "vote_average": 6.9,
    "vote_count": 39
}